.gitignore
.travis.yml
MANIFEST.in
README.rst
bootstrap.py
buildout.cfg
collective.azindexpage-configure.zcml
setup.py
travis.cfg
collective/__init__.py
collective.azindexpage.egg-info/PKG-INFO
collective.azindexpage.egg-info/SOURCES.txt
collective.azindexpage.egg-info/dependency_links.txt
collective.azindexpage.egg-info/entry_points.txt
collective.azindexpage.egg-info/namespace_packages.txt
collective.azindexpage.egg-info/not-zip-safe
collective.azindexpage.egg-info/requires.txt
collective.azindexpage.egg-info/top_level.txt
collective/azindexpage/__init__.py
collective/azindexpage/configure.zcml
collective/azindexpage/keywords.py
collective/azindexpage/rebuild_i18n.sh
collective/azindexpage/setuphandlers.py
collective/azindexpage/testing.py
collective/azindexpage/browser/__init__.py
collective/azindexpage/browser/configure.zcml
collective/azindexpage/browser/interfaces.py
collective/azindexpage/browser/page.css
collective/azindexpage/browser/page.js
collective/azindexpage/browser/page.pt
collective/azindexpage/browser/page.py
collective/azindexpage/locales/collective.azindexpage.pot
collective/azindexpage/locales/en/LC_MESSAGES/collective.azindexpage.po
collective/azindexpage/locales/fr/LC_MESSAGES/collective.azindexpage.po
collective/azindexpage/locales/nl/LC_MESSAGES/collective.azindexpage.po
collective/azindexpage/profiles/default/browserlayer.xml
collective/azindexpage/profiles/default/catalog.xml
collective/azindexpage/profiles/default/collective.azindexpage.marker.txt
collective/azindexpage/profiles/default/cssregistry.xml
collective/azindexpage/profiles/default/jsregistry.xml
collective/azindexpage/profiles/default/metadata.xml
collective/azindexpage/profiles/default/types.xml
collective/azindexpage/profiles/default/types/Document.xml
collective/azindexpage/tests/__init__.py
collective/azindexpage/tests/base.py
collective/azindexpage/tests/test_page.py
collective/azindexpage/tests/test_setup.py
collective/azindexpage/tests/utils.py
collective/azindexpage/upgrades/__init__.py
collective/azindexpage/upgrades/configure.zcml
collective/azindexpage/upgrades/v1x.py
docs/HISTORY.txt