Metadata-Version: 1.0
Name: collective.azindexpage
Version: 1.0.3
Summary: Create a A-Z index page for Plone
Home-page: https://github.com/toutpt/collective.azindexpage
Author: JeanMichel FRANCOIS aka toutpt
Author-email: toutpt@gmail.com
License: GPL
Keywords: plone lingua index
Platform: UNKNOWN
Classifier: Programming Language :: Python
Classifier: Framework :: Plone
Classifier: Framework :: Plone :: 4.0
Classifier: Framework :: Plone :: 4.1
Classifier: Framework :: Plone :: 4.2
